pyas/DataCursorFrame.py
pyas/ImgDisplayFrame.py
pyas/PilotFrame.py
pyas/__init__.py
pyas/__main__.py
pyas/controller.py
pyas/main_backup.py
pyas/model.py
pyas/qrc_resources.py
pyas/resources.qrc
pyas/view.py
pyas/resources/About_logo.jpg
pyas/resources/PyAs_main_window.svg
pyas/resources/figure_change_title.svg
pyas/resources/figure_show_title_within_image.svg
pyas/resources/file_exit.svg
pyas/resources/file_open.svg
pyas/resources/file_save.svg
pyas/resources/help_about.svg
pyas/resources/help_content.svg
pyas/resources/main_window.jpg
pyas/resources/main_window.png
pyas/resources/main_window_v1.jpg
pyas/resources/operation_FFT.svg
pyas/resources/operation_FFTShift.svg
pyas/resources/operation_Fourier_transform.svg
pyas/resources/operation_anticlockwise_rotation_90.svg
pyas/resources/operation_clockwise_rotation_90.svg
pyas/resources/operation_conjugate.svg
pyas/resources/operation_flip_horizontal.svg
pyas/resources/operation_flip_vertical.svg
pyas/resources/operation_iFFT.svg
pyas/resources/operation_iFFTShift.svg
pyas/resources/operation_permute.svg
pyas/resources/operation_reset.svg
pyas/resources/operation_reshape.svg
pyas/resources/operation_squeeze.svg
pyas/resources/view_playVideo.svg
PyArrShow-1.0.8.dist-info/LICENSE
PyArrShow-1.0.8.dist-info/METADATA
PyArrShow-1.0.8.dist-info/WHEEL
PyArrShow-1.0.8.dist-info/entry_points.txt
PyArrShow-1.0.8.dist-info/top_level.txt
PyArrShow-1.0.8.dist-info/RECORD
