Metadata-Version: 2.1
Name: PyArrShow
Version: 1.0.8
Summary: Python ArrayShow for MRI data visualization.
Author-email: "Kaixuan,Zhao" <kaixuan_zhao@163.com>
Project-URL: Homepage, https://github.com/15625148866/PyArrShow
Project-URL: Bug Tracker, https://github.com/15625148866/PyArrShow/issues
Classifier: Programming Language :: Python :: 3
Classifier: License :: OSI Approved :: MIT License
Classifier: Operating System :: OS Independent
Requires-Python: >=3.8
License-File: LICENSE
Requires-Dist: numpy
Requires-Dist: pyside6
